openchat/__init__.py
openchat/openchat.py
openchat/agents/__init__.py
openchat/agents/blender.py
openchat/agents/dialogpt.py
openchat/agents/dodecathlon.py
openchat/agents/gptneo.py
openchat/agents/reddit.py
openchat/agents/safety.py
openchat/agents/unlikelihood.py
openchat/agents/wow.py
openchat/base/__init__.py
openchat/base/agents/__init__.py
openchat/base/agents/base.py
openchat/base/agents/convai2.py
openchat/base/agents/huggingface.py
openchat/base/agents/parlai.py
openchat/base/agents/prompt.py
openchat/base/agents/wow.py
openchat/base/envs/__init__.py
openchat/base/envs/base.py
openchat/envs/__init__.py
openchat/envs/interactive.py
openchat/utils/__init__.py
openchat/utils/class_utils.py
openchat/utils/terminal_utils.py
tests/__init__.py
tests/interactive_test.py
tests/model_test.py
openchat-1.1.12.dist-info/LICENSE
openchat-1.1.12.dist-info/METADATA
openchat-1.1.12.dist-info/WHEEL
openchat-1.1.12.dist-info/top_level.txt
openchat-1.1.12.dist-info/RECORD
